seisgen/DDGFMgr.py
seisgen/DPointMgr.py
seisgen/DSGTMgr.py
seisgen/__init__.py
seisgen/MTTools/DLune.py
seisgen/MTTools/DMomentTensors.py
seisgen/MTTools/DOrientations.py
seisgen/MTTools/__init__.py
seisgen/greens_function/__init__.py
seisgen/greens_function/dgf_reader.py
seisgen/greens_function/sgt_reader.py
seisgen/math/__init__.py
seisgen/math/interp_tools.py
seisgen/seismic/DSyn.py
seisgen/seismic/__init__.py
seisgen/util_SPECFEM3D/__init__.py
seisgen/util_SPECFEM3D/ibool_reader.py
seisgen/util_SPECFEM3D/xyz_reader.py
seisgen-0.2.1.dist-info/LICENSE
seisgen-0.2.1.dist-info/METADATA
seisgen-0.2.1.dist-info/WHEEL
seisgen-0.2.1.dist-info/top_level.txt
seisgen-0.2.1.dist-info/RECORD
